sturnus/__init__.py
sturnus/__main__.py
sturnus/__version__.py
sturnus/core.py
sturnus-0.1.8.dist-info/METADATA
sturnus-0.1.8.dist-info/WHEEL
sturnus-0.1.8.dist-info/entry_points.txt
sturnus-0.1.8.dist-info/licenses/LICENSE
sturnus-0.1.8.dist-info/RECORD
