Metadata-Version: 2.4
Name: sturnus
Version: 0.1.8
Summary: A Python library for demonstration and publishing to PyPI.
License-File: LICENSE
Keywords: starling,sturnus
Author: Starling Associates
Author-email: info@starling.studio
Maintainer: Lars van Vianen
Maintainer-email: lars@starling.studio
Requires-Python: >=3.12,<4.0
Classifier: Development Status :: 5 - Production/Stable
Classifier: Intended Audience :: Developers
Classifier: License :: Other/Proprietary License
Classifier: Natural Language :: English
Classifier: Operating System :: OS Independent
Classifier: Environment :: Web Environment
Classifier: Framework :: Django
Classifier: Programming Language :: Python :: 3
Classifier: Programming Language :: Python :: 3 :: Only
Classifier: Programming Language :: Python :: 3.12
Classifier: Programming Language :: Python :: 3.13
Classifier: Programming Language :: Python :: 3.14
Classifier: Topic :: Software Development :: Libraries :: Python Modules
Classifier: Topic :: Software Development :: Libraries :: Application Frameworks
Classifier: Topic :: Internet :: WWW/HTTP
Classifier: Topic :: Internet :: WWW/HTTP :: Dynamic Content
Classifier: Topic :: Internet :: WWW/HTTP :: WSGI
Requires-Dist: django (>=6.0.0,<7)
Requires-Dist: rite (>=0.2.4)
Project-URL: Documentation, https://github.com/starling-cloud/sturnus-dev/doc
Project-URL: Homepage, https://starling.cloud/
Project-URL: Repository, https://github.com/starling-cloud/sturnus-dev
